{
	"info": {
		"_postman_id": "2d720405-5335-477c-a410-be5e06a2082a",
		"name": "Trello API",
		"schema": "https://schema.getpostman.com/json/collection/v2.1.0/collection.json",
		"_exporter_id": "37952252"
	},
	"item": [
		{
			"name": "Get all boards",
			"event": [
				{
					"listen": "test",
					"script": {
						"exec": [
							"pm.test(\"Status code is 200\", function () {",
							"    pm.response.to.have.status(200);",
							"});",
							"",
							"// Uncomment these to be able to delete all existing boards",
							"// const existingBoardIds = response.map(board => board.id);",
							"// pm.collectionVariables.set('existingBoardIds', existingBoardIds);"
						],
						"type": "text/javascript",
						"packages": {}
					}
				}
			],
			"request": {
				"method": "GET",
				"header": [],
				"url": {
					"raw": "{{baseUrl}}/1/members/me/boards?key={{trelloKey}}&token={{trelloToken}}",
					"host": [
						"{{baseUrl}}"
					],
					"path": [
						"1",
						"members",
						"me",
						"boards"
					],
					"query": [
						{
							"key": "key",
							"value": "{{trelloKey}}"
						},
						{
							"key": "token",
							"value": "{{trelloToken}}"
						}
					]
				}
			},
			"response": []
		},
		{
			"name": "Create board",
			"event": [
				{
					"listen": "test",
					"script": {
						"exec": [
							"pm.test(\"Status code is 200\", function () {",
							"    pm.response.to.have.status(200);",
							"});",
							"",
							"let response;",
							"",
							"pm.test ('Board is created', () => {",
							"    response = pm.response.json();",
							"    pm.expect(response).to.be.an('object');",
							"    pm.expect(response).to.haveOwnProperty('name');",
							"    pm.expect(response.name).to.eql(pm.collectionVariables.get('randomBoardName'));",
							"});",
							"",
							"pm.test ('Board is private', () => {",
							"    pm.expect(response.prefs.permissionLevel).to.eql('private');",
							"});",
							"",
							"pm.test ('Calendar is disabled', () => {",
							"    const calendarView = response.prefs.switcherViews.find(view => view.viewType === 'Calendar');",
							"    pm.expect(calendarView).to.be.an('object');",
							"    pm.expect(calendarView.enabled).to.be.false;",
							"});",
							"",
							"pm.collectionVariables.set('boardId', response.id);"
						],
						"type": "text/javascript",
						"packages": {}
					}
				},
				{
					"listen": "prerequest",
					"script": {
						"exec": [
							"const randomBoardName =  pm.variables.replaceIn('{{$randomCatchPhrase}}');",
							"pm.collectionVariables.set('randomBoardName', randomBoardName);"
						],
						"type": "text/javascript",
						"packages": {}
					}
				}
			],
			"request": {
				"method": "POST",
				"header": [],
				"url": {
					"raw": "{{baseUrl}}/1/boards/?name={{randomBoardName}}&key={{trelloKey}}&token={{trelloToken}}",
					"host": [
						"{{baseUrl}}"
					],
					"path": [
						"1",
						"boards",
						""
					],
					"query": [
						{
							"key": "name",
							"value": "{{randomBoardName}}"
						},
						{
							"key": "key",
							"value": "{{trelloKey}}"
						},
						{
							"key": "token",
							"value": "{{trelloToken}}"
						}
					]
				}
			},
			"response": []
		},
		{
			"name": "Get a board",
			"event": [
				{
					"listen": "test",
					"script": {
						"exec": [
							"pm.test(\"Status code is 200\", function () {",
							"    pm.response.to.have.status(200);",
							"});"
						],
						"type": "text/javascript",
						"packages": {}
					}
				}
			],
			"request": {
				"auth": {
					"type": "noauth"
				},
				"method": "GET",
				"header": [
					{
						"key": "Accept",
						"value": "application/json"
					}
				],
				"url": {
					"raw": "{{baseUrl}}/1/boards/:id?key={{trelloKey}}&token={{trelloToken}}",
					"host": [
						"{{baseUrl}}"
					],
					"path": [
						"1",
						"boards",
						":id"
					],
					"query": [
						{
							"key": "key",
							"value": "{{trelloKey}}"
						},
						{
							"key": "token",
							"value": "{{trelloToken}}"
						}
					],
					"variable": [
						{
							"key": "id",
							"value": "{{boardId}}"
						}
					]
				}
			},
			"response": []
		},
		{
			"name": "Create To Do list",
			"event": [
				{
					"listen": "test",
					"script": {
						"exec": [
							"pm.test(\"Status code is 200\", function () {",
							"    pm.response.to.have.status(200);",
							"});",
							"",
							"const response = pm.response.json();",
							"",
							"pm.test('TODO list is created', () => {",
							"    pm.expect(response.name).to.eql('To Do');",
							"    pm.expect(response.closed).to.be.false;",
							"    pm.expect(response.idBoard).to.be.eql(pm.collectionVariables.get('boardId'));",
							"}); ",
							"",
							"pm.collectionVariables.set('todoListId', response.id); "
						],
						"type": "text/javascript",
						"packages": {}
					}
				},
				{
					"listen": "prerequest",
					"script": {
						"exec": [
							""
						],
						"type": "text/javascript",
						"packages": {}
					}
				}
			],
			"request": {
				"method": "POST",
				"header": [],
				"url": {
					"raw": "{{baseUrl}}/1/boards/:id/lists?name=To Do&key={{trelloKey}}&token={{trelloToken}}",
					"host": [
						"{{baseUrl}}"
					],
					"path": [
						"1",
						"boards",
						":id",
						"lists"
					],
					"query": [
						{
							"key": "name",
							"value": "To Do"
						},
						{
							"key": "key",
							"value": "{{trelloKey}}"
						},
						{
							"key": "token",
							"value": "{{trelloToken}}"
						}
					],
					"variable": [
						{
							"key": "id",
							"value": "{{boardId}}"
						}
					]
				}
			},
			"response": []
		},
		{
			"name": "Create Done list",
			"event": [
				{
					"listen": "test",
					"script": {
						"exec": [
							"pm.test(\"Status code is 200\", function () {",
							"    pm.response.to.have.status(200);",
							"});",
							"",
							"const response = pm.response.json();",
							"",
							"pm.test('Done list is created', () => {",
							"    pm.expect(response.name).to.eql('Done');",
							"    pm.expect(response.closed).to.be.false;",
							"    pm.expect(response.idBoard).to.be.eql(pm.collectionVariables.get('boardId'));",
							"}); ",
							"",
							"pm.collectionVariables.set('doneListId', response.id);"
						],
						"type": "text/javascript",
						"packages": {}
					}
				}
			],
			"request": {
				"method": "POST",
				"header": [],
				"url": {
					"raw": "{{baseUrl}}/1/boards/:id/lists?name=Done&key={{trelloKey}}&token={{trelloToken}}",
					"host": [
						"{{baseUrl}}"
					],
					"path": [
						"1",
						"boards",
						":id",
						"lists"
					],
					"query": [
						{
							"key": "name",
							"value": "Done"
						},
						{
							"key": "key",
							"value": "{{trelloKey}}"
						},
						{
							"key": "token",
							"value": "{{trelloToken}}"
						}
					],
					"variable": [
						{
							"key": "id",
							"value": "{{boardId}}"
						}
					]
				}
			},
			"response": []
		},
		{
			"name": "Get lists on a board",
			"event": [
				{
					"listen": "test",
					"script": {
						"exec": [
							"pm.test(\"Status code is 200\", function () {",
							"    pm.response.to.have.status(200);",
							"});"
						],
						"type": "text/javascript",
						"packages": {}
					}
				}
			],
			"request": {
				"method": "GET",
				"header": [
					{
						"key": "Accept",
						"value": "application/json"
					}
				],
				"url": {
					"raw": "{{baseUrl}}/1/boards/:id/lists?key={{trelloKey}}&token={{trelloToken}}",
					"host": [
						"{{baseUrl}}"
					],
					"path": [
						"1",
						"boards",
						":id",
						"lists"
					],
					"query": [
						{
							"key": "key",
							"value": "{{trelloKey}}"
						},
						{
							"key": "token",
							"value": "{{trelloToken}}"
						}
					],
					"variable": [
						{
							"key": "id",
							"value": "{{boardId}}"
						}
					]
				}
			},
			"response": []
		},
		{
			"name": "Create a new Card",
			"event": [
				{
					"listen": "test",
					"script": {
						"exec": [
							"pm.test(\"Status code is 200\", function () {",
							"    pm.response.to.have.status(200);",
							"});",
							"",
							"const response = pm.response.json();",
							"",
							"pm.test('Card is created', () => {",
							"    pm.expect(response.name).to.eql(pm.collectionVariables.get(\"randomCardName\"));",
							"    pm.expect(response.idList).to.eql(pm.collectionVariables.get('todoListId'));",
							"    pm.expect(response.idBoard).to.be.eql(pm.collectionVariables.get('boardId'));",
							"    pm.expect(response.badges.attachmentsByType.trello.card).to.be.eql(0);",
							"});",
							"",
							"pm.collectionVariables.set('cardId', response.id);"
						],
						"type": "text/javascript",
						"packages": {}
					}
				},
				{
					"listen": "prerequest",
					"script": {
						"exec": [
							"const randomCardName =  pm.variables.replaceIn('{{$randomCatchPhraseAdjective}}');",
							"pm.collectionVariables.set('randomCardName', randomCardName);"
						],
						"type": "text/javascript",
						"packages": {}
					}
				}
			],
			"request": {
				"method": "POST",
				"header": [],
				"url": {
					"raw": "{{baseUrl}}/1/cards?idList={{todoListId}}&key={{trelloKey}}&token={{trelloToken}}&name={{randomCardName}}",
					"host": [
						"{{baseUrl}}"
					],
					"path": [
						"1",
						"cards"
					],
					"query": [
						{
							"key": "idList",
							"value": "{{todoListId}}"
						},
						{
							"key": "key",
							"value": "{{trelloKey}}"
						},
						{
							"key": "token",
							"value": "{{trelloToken}}"
						},
						{
							"key": "name",
							"value": "{{randomCardName}}"
						}
					]
				}
			},
			"response": []
		},
		{
			"name": "Get list of a card",
			"event": [
				{
					"listen": "test",
					"script": {
						"exec": [
							"pm.test(\"Status code is 200\", function () {",
							"    pm.response.to.have.status(200);",
							"});"
						],
						"type": "text/javascript",
						"packages": {}
					}
				}
			],
			"request": {
				"method": "GET",
				"header": [
					{
						"key": "Accept",
						"value": "application/json"
					}
				],
				"url": {
					"raw": "{{baseUrl}}/1/cards/:id/list?key={{trelloKey}}&token={{trelloToken}}",
					"host": [
						"{{baseUrl}}"
					],
					"path": [
						"1",
						"cards",
						":id",
						"list"
					],
					"query": [
						{
							"key": "key",
							"value": "{{trelloKey}}"
						},
						{
							"key": "token",
							"value": "{{trelloToken}}"
						}
					],
					"variable": [
						{
							"key": "id",
							"value": "{{cardId}}"
						}
					]
				}
			},
			"response": []
		},
		{
			"name": "Move card to Done list",
			"event": [
				{
					"listen": "test",
					"script": {
						"exec": [
							"pm.test(\"Status code is 200\", function () {",
							"    pm.response.to.have.status(200);",
							"});",
							"",
							"const response = pm.response.json();",
							"",
							"pm.test('Card is moved', () => {",
							"    pm.expect(response.name).to.be.eql(pm.collectionVariables.get('randomCardName'));",
							"    pm.expect(response.idList).to.be.eql(pm.collectionVariables.get('doneListId'));",
							"});"
						],
						"type": "text/javascript",
						"packages": {}
					}
				}
			],
			"request": {
				"method": "PUT",
				"header": [],
				"url": {
					"raw": "{{baseUrl}}/1/cards/:id?key={{trelloKey}}&token={{trelloToken}}&idList={{doneListId}}",
					"host": [
						"{{baseUrl}}"
					],
					"path": [
						"1",
						"cards",
						":id"
					],
					"query": [
						{
							"key": "key",
							"value": "{{trelloKey}}"
						},
						{
							"key": "token",
							"value": "{{trelloToken}}"
						},
						{
							"key": "idList",
							"value": "{{doneListId}}"
						}
					],
					"variable": [
						{
							"key": "id",
							"value": "{{cardId}}"
						}
					]
				}
			},
			"response": []
		},
		{
			"name": "Delete a board",
			"event": [
				{
					"listen": "test",
					"script": {
						"exec": [
							"pm.test(\"Status code is 200\", function () {",
							"    pm.response.to.have.status(200);",
							"});"
						],
						"type": "text/javascript",
						"packages": {}
					}
				},
				{
					"listen": "prerequest",
					"script": {
						"exec": [
							"// This code will remove all existing boards one at a time ",
							"// Prior to execution uncomment lines 6 and 7 on the \"Get all boards\" call, and run that first.",
							"",
							"// const existingBoardIds = pm.collectionVariables.get('existingBoardIds');",
							"// const boardId = existingBoardIds.pop();",
							"// pm.collectionVariables.set('boardId', boardId);",
							"// pm.collectionVariables.set('existingBoardIds', existingBoardIds);"
						],
						"type": "text/javascript",
						"packages": {}
					}
				}
			],
			"request": {
				"method": "DELETE",
				"header": [],
				"url": {
					"raw": "{{baseUrl}}/1/boards/:id?key={{trelloKey}}&token={{trelloToken}}",
					"host": [
						"{{baseUrl}}"
					],
					"path": [
						"1",
						"boards",
						":id"
					],
					"query": [
						{
							"key": "key",
							"value": "{{trelloKey}}"
						},
						{
							"key": "token",
							"value": "{{trelloToken}}"
						}
					],
					"variable": [
						{
							"key": "id",
							"value": "{{boardId}}"
						}
					]
				}
			},
			"response": []
		},
		{
			"name": "Get deleted board",
			"event": [
				{
					"listen": "test",
					"script": {
						"exec": [
							"pm.test(\"Status code is 404\", function () {",
							"    pm.response.to.have.status(404);",
							"});"
						],
						"type": "text/javascript",
						"packages": {}
					}
				}
			],
			"request": {
				"method": "GET",
				"header": [
					{
						"key": "Accept",
						"value": "application/json"
					}
				],
				"url": {
					"raw": "{{baseUrl}}/1/boards/:id?key={{trelloKey}}&token={{trelloToken}}",
					"host": [
						"{{baseUrl}}"
					],
					"path": [
						"1",
						"boards",
						":id"
					],
					"query": [
						{
							"key": "key",
							"value": "{{trelloKey}}"
						},
						{
							"key": "token",
							"value": "{{trelloToken}}"
						}
					],
					"variable": [
						{
							"key": "id",
							"value": "{{boardId}}"
						}
					]
				}
			},
			"response": []
		}
	],
	"auth": {
		"type": "inherit"
	},
	"event": [
		{
			"listen": "prerequest",
			"script": {
				"type": "text/javascript",
				"packages": {},
				"exec": [
					""
				]
			}
		},
		{
			"listen": "test",
			"script": {
				"type": "text/javascript",
				"packages": {},
				"exec": [
					""
				]
			}
		}
	],
	"variable": [
		{
			"key": "baseUrl",
			"value": "https://api.trello.com",
			"type": "string"
		},
		{
			"key": "trelloToken",
			"value": "Your token here"
		},
		{
			"key": "trelloKey",
			"value": "Your key here"
		},
		{
			"key": "boardId",
			"value": ""
		},
		{
			"key": "todoListId",
			"value": ""
		},
		{
			"key": "doneListId",
			"value": ""
		},
		{
			"key": "cardId",
			"value": ""
		},
		{
			"key": "randomBoardName",
			"value": ""
		},
		{
			"key": "existingBoardIds",
			"value": ""
		},
		{
			"key": "randomCardName",
			"value": ""
		}
	]
}
